HISTORY.rst
LICENSE
MANIFEST.in
README.rst
setup.py
pystrainer.egg-info/PKG-INFO
pystrainer.egg-info/SOURCES.txt
pystrainer.egg-info/dependency_links.txt
pystrainer.egg-info/not-zip-safe
pystrainer.egg-info/requires.txt
pystrainer.egg-info/top_level.txt
strainer/__init__.py
strainer/context.py
strainer/exceptions.py
strainer/fields.py
strainer/formatters.py
strainer/structure.py
strainer/validators.py